{"chapters":[{"id":34318,"views":73,"price":0,"name":"Chapter 247","hidden":0,"last_update":"2024-04-20 14:05:51","slug":"chapter-247","name_extend":null},{"id":33962,"views":28,"price":null,"name":"Chapter 246","hidden":0,"last_update":"2024-04-18 21:42:18","slug":"chapter-246","name_extend":""},{"id":33961,"views":17,"price":null,"name":"Chapter 245","hidden":0,"last_update":"2024-04-18 21:41:07","slug":"chapter-245","name_extend":""}],"genres":[{"name":"Manhua","slug":"manhua","id":3,"taxonomy":"genres"},{"name":"Action","slug":"action","id":7,"taxonomy":"genres"},{"name":"Truy\u1ec7n M\u00e0u","slug":"truyen-mau","id":11,"taxonomy":"genres"},{"name":"Adventure","slug":"adventure","id":23,"taxonomy":"genres"}]}