{"chapters":[{"id":40744,"views":46,"price":null,"name":"Chapter 673","hidden":0,"last_update":"2024-05-15 00:40:13","slug":"chapter-673","name_extend":""},{"id":40743,"views":18,"price":null,"name":"Chapter 672","hidden":0,"last_update":"2024-05-15 00:40:07","slug":"chapter-672","name_extend":""},{"id":40742,"views":14,"price":null,"name":"Chapter 671","hidden":0,"last_update":"2024-05-15 00:36:04","slug":"chapter-671","name_extend":""}],"genres":[{"name":"Manhua","slug":"manhua","id":3,"taxonomy":"genres"},{"name":"Action","slug":"action","id":7,"taxonomy":"genres"},{"name":"Fantasy","slug":"fantasy","id":24,"taxonomy":"genres"}]}