{"chapters":[{"id":43236,"views":262,"price":0,"name":"Chapter 135","hidden":0,"last_update":"2024-05-16 18:32:39","slug":"chapter-135","name_extend":null},{"id":43235,"views":122,"price":null,"name":"Chapter 134","hidden":0,"last_update":"2024-05-16 18:32:24","slug":"chapter-134","name_extend":""},{"id":43234,"views":98,"price":null,"name":"Chapter 133","hidden":0,"last_update":"2024-05-16 18:32:01","slug":"chapter-133","name_extend":""}],"genres":[{"name":"Manhua","slug":"manhua","id":3,"taxonomy":"genres"},{"name":"Horror","slug":"horror","id":5,"taxonomy":"genres"},{"name":"Mystery","slug":"mystery","id":9,"taxonomy":"genres"},{"name":"Truy\u1ec7n M\u00e0u","slug":"truyen-mau","id":11,"taxonomy":"genres"}]}